[
  {
    "candle_index": 56,
    "zone_top": 80376.0,
    "zone_bottom": 80244.1,
    "vwap_at_detection": 80306.67966578521,
    "detection_timestamp": 1778279699999,
    "direction": "bearish",
    "key_candle": {
      "index": 56,
      "open": 80304.5,
      "high": 80335.5,
      "low": 80280.0,
      "close": 80290.3,
      "volume": 207.499,
      "vol_z_score": 0.5268458664550433,
      "body_percentage": 25.585585585580343,
      "upper_wick_pct": 55.85585585585586,
      "lower_wick_pct": 18.558558558563803,
      "rejection_direction": "UP",
      "timestamp": 1778279400000
    },
    "accumulation_zone": {
      "start_idx": 51,
      "end_idx": 56,
      "high": 80376.0,
      "low": 80244.1,
      "volume_avg": 200.19459999999998,
      "vwap": 80306.67966578521,
      "mfi": 50,
      "quality_score": 1.0134674425048615
    },
    "mini_trend": {
      "start_idx": 50,
      "end_idx": 69,
      "direction": "bearish",
      "start_price": 80274.3,
      "end_price": 80094.0,
      "slope": -10.433233082708384,
      "slope_normalized": 0.013002663389849829,
      "r2": 0.765790098171516
    },
    "atr_at_detection": 255.3000000000029,
    "lifecycle_state": "active",
    "touch_count": 0,
    "polarity_flipped": false,
    "zone_id": ""
  },
  {
    "candle_index": 100,
    "zone_top": 80405.0,
    "zone_bottom": 80280.0,
    "vwap_at_detection": 80348.65962670062,
    "detection_timestamp": 1778292899999,
    "direction": "bullish",
    "key_candle": {
      "index": 100,
      "open": 80419.9,
      "high": 80432.1,
      "low": 80368.1,
      "close": 80400.0,
      "volume": 191.724,
      "vol_z_score": 0.8268409448843185,
      "body_percentage": 31.093749999990905,
      "upper_wick_pct": 19.06250000001819,
      "lower_wick_pct": 49.843749999990905,
      "rejection_direction": "DOWN",
      "timestamp": 1778292600000
    },
    "accumulation_zone": {
      "start_idx": 94,
      "end_idx": 99,
      "high": 80405.0,
      "low": 80280.0,
      "volume_avg": 204.87219999999996,
      "vwap": 80348.65962670062,
      "mfi": 50,
      "quality_score": 0.9838492243949342
    },
    "mini_trend": {
      "start_idx": 88,
      "end_idx": 113,
      "direction": "bullish",
      "start_price": 80287.3,
      "end_price": 80445.1,
      "slope": 5.52854700854566,
      "slope_normalized": 0.006880543012742217,
      "r2": 0.5400600786828382
    },
    "atr_at_detection": 254.70000000001164,
    "lifecycle_state": "active",
    "touch_count": 0,
    "polarity_flipped": false,
    "zone_id": ""
  },
  {
    "candle_index": 102,
    "zone_top": 80405.0,
    "zone_bottom": 80280.0,
    "vwap_at_detection": 80348.65962670062,
    "detection_timestamp": 1778293499999,
    "direction": "bullish",
    "key_candle": {
      "index": 102,
      "open": 80369.0,
      "high": 80392.5,
      "low": 80348.6,
      "close": 80360.5,
      "volume": 188.315,
      "vol_z_score": 0.8264824875409557,
      "body_percentage": 19.362186788157466,
      "upper_wick_pct": 53.530751708435346,
      "lower_wick_pct": 27.10706150340719,
      "rejection_direction": "UP",
      "timestamp": 1778293200000
    },
    "accumulation_zone": {
      "start_idx": 94,
      "end_idx": 99,
      "high": 80405.0,
      "low": 80280.0,
      "volume_avg": 204.87219999999996,
      "vwap": 80348.65962670062,
      "mfi": 50,
      "quality_score": 0.9705158910616009
    },
    "mini_trend": {
      "start_idx": 88,
      "end_idx": 113,
      "direction": "bullish",
      "start_price": 80287.3,
      "end_price": 80445.1,
      "slope": 5.52854700854566,
      "slope_normalized": 0.006880543012742217,
      "r2": 0.5400600786828382
    },
    "atr_at_detection": 233.90000000000873,
    "lifecycle_state": "active",
    "touch_count": 0,
    "polarity_flipped": false,
    "zone_id": ""
  },
  {
    "candle_index": 104,
    "zone_top": 80432.1,
    "zone_bottom": 80340.4,
    "vwap_at_detection": 80385.26445450817,
    "detection_timestamp": 1778294099999,
    "direction": "bullish",
    "key_candle": {
      "index": 104,
      "open": 80387.6,
      "high": 80448.2,
      "low": 80384.1,
      "close": 80385.7,
      "volume": 217.95,
      "vol_z_score": 1.209525514868704,
      "body_percentage": 2.9641185647566144,
      "upper_wick_pct": 94.53978159126291,
      "lower_wick_pct": 2.4960998439804785,
      "rejection_direction": "UP",
      "timestamp": 1778293800000
    },
    "accumulation_zone": {
      "start_idx": 99,
      "end_idx": 104,
      "high": 80432.1,
      "low": 80340.4,
      "volume_avg": 178.7274,
      "vwap": 80385.26445450817,
      "mfi": 50,
      "quality_score": 1.0840123056216275
    },
    "mini_trend": {
      "start_idx": 88,
      "end_idx": 113,
      "direction": "bullish",
      "start_price": 80287.3,
      "end_price": 80445.1,
      "slope": 5.52854700854566,
      "slope_normalized": 0.006880543012742217,
      "r2": 0.5400600786828382
    },
    "atr_at_detection": 250.0,
    "lifecycle_state": "active",
    "touch_count": 0,
    "polarity_flipped": false,
    "zone_id": ""
  },
  {
    "candle_index": 176,
    "zone_top": 80381.3,
    "zone_bottom": 80294.1,
    "vwap_at_detection": 80349.29289691645,
    "detection_timestamp": 1778315699999,
    "direction": "bearish",
    "key_candle": {
      "index": 176,
      "open": 80371.1,
      "high": 80400.3,
      "low": 80371.0,
      "close": 80380.0,
      "volume": 331.265,
      "vol_z_score": 0.5214148649825435,
      "body_percentage": 30.375426621137525,
      "upper_wick_pct": 69.28327645051499,
      "lower_wick_pct": 0.34129692834747727,
      "rejection_direction": "UP",
      "timestamp": 1778315400000
    },
    "accumulation_zone": {
      "start_idx": 171,
      "end_idx": 176,
      "high": 80381.3,
      "low": 80294.1,
      "volume_avg": 189.6688,
      "vwap": 80349.29289691645,
      "mfi": 50,
      "quality_score": 1.062354871452616
    },
    "mini_trend": {
      "start_idx": 170,
      "end_idx": 191,
      "direction": "bearish",
      "start_price": 80341.0,
      "end_price": 80181.0,
      "slope": -8.494127611518593,
      "slope_normalized": 0.010575265318684617,
      "r2": 0.5552896950206794
    },
    "atr_at_detection": 273.40000000000873,
    "lifecycle_state": "active",
    "touch_count": 0,
    "polarity_flipped": false,
    "zone_id": ""
  },
  {
    "candle_index": 178,
    "zone_top": 80422.3,
    "zone_bottom": 80336.9,
    "vwap_at_detection": 80378.54884476746,
    "detection_timestamp": 1778316299999,
    "direction": "bearish",
    "key_candle": {
      "index": 178,
      "open": 80396.1,
      "high": 80404.1,
      "low": 80360.0,
      "close": 80400.0,
      "volume": 353.865,
      "vol_z_score": 0.6066347530133176,
      "body_percentage": 8.84353741495162,
      "upper_wick_pct": 9.297052154206984,
      "lower_wick_pct": 81.8594104308414,
      "rejection_direction": "DOWN",
      "timestamp": 1778316000000
    },
    "accumulation_zone": {
      "start_idx": 173,
      "end_idx": 178,
      "high": 80422.3,
      "low": 80336.9,
      "volume_avg": 204.2244,
      "vwap": 80378.54884476746,
      "mfi": 50,
      "quality_score": 1.055093202235661
    },
    "mini_trend": {
      "start_idx": 170,
      "end_idx": 191,
      "direction": "bearish",
      "start_price": 80341.0,
      "end_price": 80181.0,
      "slope": -8.494127611518593,
      "slope_normalized": 0.010575265318684617,
      "r2": 0.5552896950206794
    },
    "atr_at_detection": 295.40000000000873,
    "lifecycle_state": "active",
    "touch_count": 0,
    "polarity_flipped": false,
    "zone_id": ""
  },
  {
    "candle_index": 260,
    "zone_top": 80312.6,
    "zone_bottom": 80190.0,
    "vwap_at_detection": 80258.216233361,
    "detection_timestamp": 1778340899999,
    "direction": "bullish",
    "key_candle": {
      "index": 260,
      "open": 80375.0,
      "high": 80449.3,
      "low": 80374.9,
      "close": 80404.0,
      "volume": 350.439,
      "vol_z_score": 1.1495600560546764,
      "body_percentage": 38.978494623651336,
      "upper_wick_pct": 60.88709677419031,
      "lower_wick_pct": 0.13440860215834546,
      "rejection_direction": "UP",
      "timestamp": 1778340600000
    },
    "accumulation_zone": {
      "start_idx": 252,
      "end_idx": 257,
      "high": 80312.6,
      "low": 80190.0,
      "volume_avg": 269.848,
      "vwap": 80258.216233361,
      "mfi": 50,
      "quality_score": 1.000189105475199
    },
    "mini_trend": {
      "start_idx": 261,
      "end_idx": 270,
      "direction": "bullish",
      "start_price": 80487.9,
      "end_price": 80683.1,
      "slope": 19.70363636363519,
      "slope_normalized": 0.024469141058974513,
      "r2": 0.6784678384780874
    },
    "atr_at_detection": 259.3000000000029,
    "lifecycle_state": "active",
    "touch_count": 0,
    "polarity_flipped": false,
    "zone_id": ""
  },
  {
    "candle_index": 262,
    "zone_top": 80312.6,
    "zone_bottom": 80190.0,
    "vwap_at_detection": 80258.216233361,
    "detection_timestamp": 1778341499999,
    "direction": "bullish",
    "key_candle": {
      "index": 262,
      "open": 80487.9,
      "high": 80566.0,
      "low": 80415.8,
      "close": 80440.0,
      "volume": 997.7,
      "vol_z_score": 3.545101579466988,
      "body_percentage": 31.89081225032963,
      "upper_wick_pct": 51.997336884159346,
      "lower_wick_pct": 16.111850865511023,
      "rejection_direction": "UP",
      "timestamp": 1778341200000
    },
    "accumulation_zone": {
      "start_idx": 252,
      "end_idx": 257,
      "high": 80312.6,
      "low": 80190.0,
      "volume_avg": 269.848,
      "vwap": 80258.216233361,
      "mfi": 50,
      "quality_score": 0.9868557721418658
    },
    "mini_trend": {
      "start_idx": 261,
      "end_idx": 270,
      "direction": "bullish",
      "start_price": 80487.9,
      "end_price": 80683.1,
      "slope": 19.70363636363519,
      "slope_normalized": 0.024469141058974513,
      "r2": 0.6784678384780874
    },
    "atr_at_detection": 376.0,
    "lifecycle_state": "active",
    "touch_count": 0,
    "polarity_flipped": false,
    "zone_id": ""
  },
  {
    "candle_index": 270,
    "zone_top": 80542.6,
    "zone_bottom": 80439.9,
    "vwap_at_detection": 80490.681013153,
    "detection_timestamp": 1778343899999,
    "direction": "bullish",
    "key_candle": {
      "index": 270,
      "open": 80609.9,
      "high": 80796.9,
      "low": 80602.1,
      "close": 80683.1,
      "volume": 1295.319,
      "vol_z_score": 3.565478841835783,
      "body_percentage": 37.57700205339631,
      "upper_wick_pct": 58.41889117042873,
      "lower_wick_pct": 4.004106776174961,
      "rejection_direction": "UP",
      "timestamp": 1778343600000
    },
    "accumulation_zone": {
      "start_idx": 263,
      "end_idx": 268,
      "high": 80542.6,
      "low": 80439.9,
      "volume_avg": 301.8932,
      "vwap": 80490.681013153,
      "mfi": 50,
      "quality_score": 1.0580244894249944
    },
    "mini_trend": {
      "start_idx": 261,
      "end_idx": 270,
      "direction": "bullish",
      "start_price": 80487.9,
      "end_price": 80683.1,
      "slope": 19.70363636363519,
      "slope_normalized": 0.024469141058974513,
      "r2": 0.6784678384780874
    },
    "atr_at_detection": 606.8999999999942,
    "lifecycle_state": "active",
    "touch_count": 0,
    "polarity_flipped": false,
    "zone_id": ""
  },
  {
    "candle_index": 296,
    "zone_top": 80827.4,
    "zone_bottom": 80673.8,
    "vwap_at_detection": 80762.77482380903,
    "detection_timestamp": 1778351699999,
    "direction": "bearish",
    "key_candle": {
      "index": 296,
      "open": 81000.0,
      "high": 81043.2,
      "low": 80965.6,
      "close": 80984.7,
      "volume": 631.876,
      "vol_z_score": 0.5941351440845183,
      "body_percentage": 19.716494845366793,
      "upper_wick_pct": 55.67010309278602,
      "lower_wick_pct": 24.61340206184719,
      "rejection_direction": "UP",
      "timestamp": 1778351400000
    },
    "accumulation_zone": {
      "start_idx": 287,
      "end_idx": 292,
      "high": 80827.4,
      "low": 80673.8,
      "volume_avg": 259.55740000000003,
      "vwap": 80762.77482380903,
      "mfi": 50,
      "quality_score": 0.9353795379538056
    },
    "mini_trend": {
      "start_idx": 295,
      "end_idx": 302,
      "direction": "bearish",
      "start_price": 81000.1,
      "end_price": 80837.1,
      "slope": -22.096428571430053,
      "slope_normalized": 0.027314489661299728,
      "r2": 0.7517690763480274
    },
    "atr_at_detection": 400.8999999999942,
    "lifecycle_state": "active",
    "touch_count": 0,
    "polarity_flipped": false,
    "zone_id": ""
  },
  {
    "candle_index": 52,
    "zone_top": 80376.0,
    "zone_bottom": 80244.1,
    "vwap_at_detection": 80306.67966578521,
    "detection_timestamp": 1778279699999,
    "direction": "bearish",
    "key_candle": {
      "index": 52,
      "open": 80304.5,
      "high": 80335.5,
      "low": 80280.0,
      "close": 80290.3,
      "volume": 207.499,
      "vol_z_score": 0.5268458664550433,
      "body_percentage": 25.585585585580343,
      "upper_wick_pct": 55.85585585585586,
      "lower_wick_pct": 18.558558558563803,
      "rejection_direction": "UP",
      "timestamp": 1778279400000
    },
    "accumulation_zone": {
      "start_idx": 47,
      "end_idx": 52,
      "high": 80376.0,
      "low": 80244.1,
      "volume_avg": 200.19459999999998,
      "vwap": 80306.67966578521,
      "mfi": 50,
      "quality_score": 1.0134674425048615
    },
    "mini_trend": {
      "start_idx": 46,
      "end_idx": 65,
      "direction": "bearish",
      "start_price": 80274.3,
      "end_price": 80094.0,
      "slope": -10.433233082708384,
      "slope_normalized": 0.013002663389849829,
      "r2": 0.765790098171516
    },
    "atr_at_detection": 255.3000000000029,
    "lifecycle_state": "active",
    "touch_count": 0,
    "polarity_flipped": false,
    "zone_id": ""
  },
  {
    "candle_index": 96,
    "zone_top": 80405.0,
    "zone_bottom": 80280.0,
    "vwap_at_detection": 80348.65962670062,
    "detection_timestamp": 1778292899999,
    "direction": "bullish",
    "key_candle": {
      "index": 96,
      "open": 80419.9,
      "high": 80432.1,
      "low": 80368.1,
      "close": 80400.0,
      "volume": 191.724,
      "vol_z_score": 0.8268409448843185,
      "body_percentage": 31.093749999990905,
      "upper_wick_pct": 19.06250000001819,
      "lower_wick_pct": 49.843749999990905,
      "rejection_direction": "DOWN",
      "timestamp": 1778292600000
    },
    "accumulation_zone": {
      "start_idx": 90,
      "end_idx": 95,
      "high": 80405.0,
      "low": 80280.0,
      "volume_avg": 204.87219999999996,
      "vwap": 80348.65962670062,
      "mfi": 50,
      "quality_score": 0.9838492243949342
    },
    "mini_trend": {
      "start_idx": 84,
      "end_idx": 109,
      "direction": "bullish",
      "start_price": 80287.3,
      "end_price": 80445.1,
      "slope": 5.52854700854566,
      "slope_normalized": 0.006880543012742217,
      "r2": 0.5400600786828382
    },
    "atr_at_detection": 254.70000000001164,
    "lifecycle_state": "active",
    "touch_count": 0,
    "polarity_flipped": false,
    "zone_id": ""
  },
  {
    "candle_index": 98,
    "zone_top": 80405.0,
    "zone_bottom": 80280.0,
    "vwap_at_detection": 80348.65962670062,
    "detection_timestamp": 1778293499999,
    "direction": "bullish",
    "key_candle": {
      "index": 98,
      "open": 80369.0,
      "high": 80392.5,
      "low": 80348.6,
      "close": 80360.5,
      "volume": 188.315,
      "vol_z_score": 0.8264824875409557,
      "body_percentage": 19.362186788157466,
      "upper_wick_pct": 53.530751708435346,
      "lower_wick_pct": 27.10706150340719,
      "rejection_direction": "UP",
      "timestamp": 1778293200000
    },
    "accumulation_zone": {
      "start_idx": 90,
      "end_idx": 95,
      "high": 80405.0,
      "low": 80280.0,
      "volume_avg": 204.87219999999996,
      "vwap": 80348.65962670062,
      "mfi": 50,
      "quality_score": 0.9705158910616009
    },
    "mini_trend": {
      "start_idx": 84,
      "end_idx": 109,
      "direction": "bullish",
      "start_price": 80287.3,
      "end_price": 80445.1,
      "slope": 5.52854700854566,
      "slope_normalized": 0.006880543012742217,
      "r2": 0.5400600786828382
    },
    "atr_at_detection": 233.90000000000873,
    "lifecycle_state": "active",
    "touch_count": 0,
    "polarity_flipped": false,
    "zone_id": ""
  },
  {
    "candle_index": 100,
    "zone_top": 80432.1,
    "zone_bottom": 80340.4,
    "vwap_at_detection": 80385.26445450817,
    "detection_timestamp": 1778294099999,
    "direction": "bullish",
    "key_candle": {
      "index": 100,
      "open": 80387.6,
      "high": 80448.2,
      "low": 80384.1,
      "close": 80385.7,
      "volume": 217.95,
      "vol_z_score": 1.209525514868704,
      "body_percentage": 2.9641185647566144,
      "upper_wick_pct": 94.53978159126291,
      "lower_wick_pct": 2.4960998439804785,
      "rejection_direction": "UP",
      "timestamp": 1778293800000
    },
    "accumulation_zone": {
      "start_idx": 95,
      "end_idx": 100,
      "high": 80432.1,
      "low": 80340.4,
      "volume_avg": 178.7274,
      "vwap": 80385.26445450817,
      "mfi": 50,
      "quality_score": 1.0840123056216275
    },
    "mini_trend": {
      "start_idx": 84,
      "end_idx": 109,
      "direction": "bullish",
      "start_price": 80287.3,
      "end_price": 80445.1,
      "slope": 5.52854700854566,
      "slope_normalized": 0.006880543012742217,
      "r2": 0.5400600786828382
    },
    "atr_at_detection": 250.0,
    "lifecycle_state": "active",
    "touch_count": 0,
    "polarity_flipped": false,
    "zone_id": ""
  },
  {
    "candle_index": 172,
    "zone_top": 80381.3,
    "zone_bottom": 80294.1,
    "vwap_at_detection": 80349.29289691645,
    "detection_timestamp": 1778315699999,
    "direction": "bearish",
    "key_candle": {
      "index": 172,
      "open": 80371.1,
      "high": 80400.3,
      "low": 80371.0,
      "close": 80380.0,
      "volume": 331.265,
      "vol_z_score": 0.5214148649825435,
      "body_percentage": 30.375426621137525,
      "upper_wick_pct": 69.28327645051499,
      "lower_wick_pct": 0.34129692834747727,
      "rejection_direction": "UP",
      "timestamp": 1778315400000
    },
    "accumulation_zone": {
      "start_idx": 167,
      "end_idx": 172,
      "high": 80381.3,
      "low": 80294.1,
      "volume_avg": 189.6688,
      "vwap": 80349.29289691645,
      "mfi": 50,
      "quality_score": 1.062354871452616
    },
    "mini_trend": {
      "start_idx": 166,
      "end_idx": 187,
      "direction": "bearish",
      "start_price": 80341.0,
      "end_price": 80181.0,
      "slope": -8.494127611518593,
      "slope_normalized": 0.010575265318684617,
      "r2": 0.5552896950206794
    },
    "atr_at_detection": 273.40000000000873,
    "lifecycle_state": "active",
    "touch_count": 0,
    "polarity_flipped": false,
    "zone_id": ""
  },
  {
    "candle_index": 174,
    "zone_top": 80422.3,
    "zone_bottom": 80336.9,
    "vwap_at_detection": 80378.54884476746,
    "detection_timestamp": 1778316299999,
    "direction": "bearish",
    "key_candle": {
      "index": 174,
      "open": 80396.1,
      "high": 80404.1,
      "low": 80360.0,
      "close": 80400.0,
      "volume": 353.865,
      "vol_z_score": 0.6066347530133176,
      "body_percentage": 8.84353741495162,
      "upper_wick_pct": 9.297052154206984,
      "lower_wick_pct": 81.8594104308414,
      "rejection_direction": "DOWN",
      "timestamp": 1778316000000
    },
    "accumulation_zone": {
      "start_idx": 169,
      "end_idx": 174,
      "high": 80422.3,
      "low": 80336.9,
      "volume_avg": 204.2244,
      "vwap": 80378.54884476746,
      "mfi": 50,
      "quality_score": 1.055093202235661
    },
    "mini_trend": {
      "start_idx": 166,
      "end_idx": 187,
      "direction": "bearish",
      "start_price": 80341.0,
      "end_price": 80181.0,
      "slope": -8.494127611518593,
      "slope_normalized": 0.010575265318684617,
      "r2": 0.5552896950206794
    },
    "atr_at_detection": 295.40000000000873,
    "lifecycle_state": "active",
    "touch_count": 0,
    "polarity_flipped": false,
    "zone_id": ""
  },
  {
    "candle_index": 256,
    "zone_top": 80312.6,
    "zone_bottom": 80190.0,
    "vwap_at_detection": 80258.216233361,
    "detection_timestamp": 1778340899999,
    "direction": "bullish",
    "key_candle": {
      "index": 256,
      "open": 80375.0,
      "high": 80449.3,
      "low": 80374.9,
      "close": 80404.0,
      "volume": 350.439,
      "vol_z_score": 1.1495600560546764,
      "body_percentage": 38.978494623651336,
      "upper_wick_pct": 60.88709677419031,
      "lower_wick_pct": 0.13440860215834546,
      "rejection_direction": "UP",
      "timestamp": 1778340600000
    },
    "accumulation_zone": {
      "start_idx": 248,
      "end_idx": 253,
      "high": 80312.6,
      "low": 80190.0,
      "volume_avg": 269.848,
      "vwap": 80258.216233361,
      "mfi": 50,
      "quality_score": 1.000189105475199
    },
    "mini_trend": {
      "start_idx": 257,
      "end_idx": 266,
      "direction": "bullish",
      "start_price": 80487.9,
      "end_price": 80683.1,
      "slope": 19.70363636363519,
      "slope_normalized": 0.024469141058974513,
      "r2": 0.6784678384780874
    },
    "atr_at_detection": 259.3000000000029,
    "lifecycle_state": "active",
    "touch_count": 0,
    "polarity_flipped": false,
    "zone_id": ""
  },
  {
    "candle_index": 258,
    "zone_top": 80312.6,
    "zone_bottom": 80190.0,
    "vwap_at_detection": 80258.216233361,
    "detection_timestamp": 1778341499999,
    "direction": "bullish",
    "key_candle": {
      "index": 258,
      "open": 80487.9,
      "high": 80566.0,
      "low": 80415.8,
      "close": 80440.0,
      "volume": 997.7,
      "vol_z_score": 3.545101579466988,
      "body_percentage": 31.89081225032963,
      "upper_wick_pct": 51.997336884159346,
      "lower_wick_pct": 16.111850865511023,
      "rejection_direction": "UP",
      "timestamp": 1778341200000
    },
    "accumulation_zone": {
      "start_idx": 248,
      "end_idx": 253,
      "high": 80312.6,
      "low": 80190.0,
      "volume_avg": 269.848,
      "vwap": 80258.216233361,
      "mfi": 50,
      "quality_score": 0.9868557721418658
    },
    "mini_trend": {
      "start_idx": 257,
      "end_idx": 266,
      "direction": "bullish",
      "start_price": 80487.9,
      "end_price": 80683.1,
      "slope": 19.70363636363519,
      "slope_normalized": 0.024469141058974513,
      "r2": 0.6784678384780874
    },
    "atr_at_detection": 376.0,
    "lifecycle_state": "active",
    "touch_count": 0,
    "polarity_flipped": false,
    "zone_id": ""
  },
  {
    "candle_index": 266,
    "zone_top": 80542.6,
    "zone_bottom": 80439.9,
    "vwap_at_detection": 80490.681013153,
    "detection_timestamp": 1778343899999,
    "direction": "bullish",
    "key_candle": {
      "index": 266,
      "open": 80609.9,
      "high": 80796.9,
      "low": 80602.1,
      "close": 80683.1,
      "volume": 1295.319,
      "vol_z_score": 3.565478841835783,
      "body_percentage": 37.57700205339631,
      "upper_wick_pct": 58.41889117042873,
      "lower_wick_pct": 4.004106776174961,
      "rejection_direction": "UP",
      "timestamp": 1778343600000
    },
    "accumulation_zone": {
      "start_idx": 259,
      "end_idx": 264,
      "high": 80542.6,
      "low": 80439.9,
      "volume_avg": 301.8932,
      "vwap": 80490.681013153,
      "mfi": 50,
      "quality_score": 1.0580244894249944
    },
    "mini_trend": {
      "start_idx": 257,
      "end_idx": 266,
      "direction": "bullish",
      "start_price": 80487.9,
      "end_price": 80683.1,
      "slope": 19.70363636363519,
      "slope_normalized": 0.024469141058974513,
      "r2": 0.6784678384780874
    },
    "atr_at_detection": 606.8999999999942,
    "lifecycle_state": "active",
    "touch_count": 0,
    "polarity_flipped": false,
    "zone_id": ""
  },
  {
    "candle_index": 292,
    "zone_top": 80827.4,
    "zone_bottom": 80673.8,
    "vwap_at_detection": 80762.77482380903,
    "detection_timestamp": 1778351699999,
    "direction": "bearish",
    "key_candle": {
      "index": 292,
      "open": 81000.0,
      "high": 81043.2,
      "low": 80965.6,
      "close": 80984.7,
      "volume": 631.876,
      "vol_z_score": 0.5941351440845183,
      "body_percentage": 19.716494845366793,
      "upper_wick_pct": 55.67010309278602,
      "lower_wick_pct": 24.61340206184719,
      "rejection_direction": "UP",
      "timestamp": 1778351400000
    },
    "accumulation_zone": {
      "start_idx": 283,
      "end_idx": 288,
      "high": 80827.4,
      "low": 80673.8,
      "volume_avg": 259.55740000000003,
      "vwap": 80762.77482380903,
      "mfi": 50,
      "quality_score": 0.9353795379538056
    },
    "mini_trend": {
      "start_idx": 291,
      "end_idx": 298,
      "direction": "bearish",
      "start_price": 81000.1,
      "end_price": 80837.1,
      "slope": -22.096428571430053,
      "slope_normalized": 0.027314489661299728,
      "r2": 0.7517690763480274
    },
    "atr_at_detection": 400.8999999999942,
    "lifecycle_state": "active",
    "touch_count": 0,
    "polarity_flipped": false,
    "zone_id": ""
  },
  {
    "candle_index": 471,
    "zone_top": 81145.9,
    "zone_bottom": 81054.2,
    "vwap_at_detection": 81100.25184760257,
    "detection_timestamp": 1778500799999,
    "direction": "bearish",
    "key_candle": {
      "index": 471,
      "open": 81138.7,
      "high": 81172.6,
      "low": 81100.0,
      "close": 81167.1,
      "volume": 315.673,
      "vol_z_score": 0.8087489864203525,
      "body_percentage": 39.11845730028437,
      "upper_wick_pct": 7.575757575756969,
      "lower_wick_pct": 53.30578512395866,
      "rejection_direction": "DOWN",
      "timestamp": 1778500500000
    },
    "accumulation_zone": {
      "start_idx": 464,
      "end_idx": 471,
      "high": 81145.9,
      "low": 81054.2,
      "volume_avg": 244.67357142857145,
      "vwap": 81100.25184760257,
      "mfi": 50,
      "quality_score": 1.0607514036735528
    },
    "mini_trend": {
      "start_idx": 476,
      "end_idx": 481,
      "direction": "bearish",
      "start_price": 81271.2,
      "end_price": 81110.9,
      "slope": -35.051428571432545,
      "slope_normalized": 0.043169601675272576,
      "r2": 0.9548753491075234
    },
    "atr_at_detection": 312.6000000000058,
    "lifecycle_state": "active",
    "touch_count": 0,
    "polarity_flipped": false,
    "zone_id": ""
  },
  {
    "candle_index": 472,
    "zone_top": 81145.9,
    "zone_bottom": 81054.2,
    "vwap_at_detection": 81100.25184760257,
    "detection_timestamp": 1778501099999,
    "direction": "bearish",
    "key_candle": {
      "index": 472,
      "open": 81167.1,
      "high": 81218.2,
      "low": 81108.0,
      "close": 81130.4,
      "volume": 584.857,
      "vol_z_score": 3.2016682823888205,
      "body_percentage": 33.30308529946698,
      "upper_wick_pct": 46.37023593465755,
      "lower_wick_pct": 20.32667876587547,
      "rejection_direction": "UP",
      "timestamp": 1778500800000
    },
    "accumulation_zone": {
      "start_idx": 464,
      "end_idx": 471,
      "high": 81145.9,
      "low": 81054.2,
      "volume_avg": 244.67357142857145,
      "vwap": 81100.25184760257,
      "mfi": 50,
      "quality_score": 1.0540847370068862
    },
    "mini_trend": {
      "start_idx": 476,
      "end_idx": 481,
      "direction": "bearish",
      "start_price": 81271.2,
      "end_price": 81110.9,
      "slope": -35.051428571432545,
      "slope_normalized": 0.043169601675272576,
      "r2": 0.9548753491075234
    },
    "atr_at_detection": 358.1999999999971,
    "lifecycle_state": "active",
    "touch_count": 0,
    "polarity_flipped": false,
    "zone_id": ""
  },
  {
    "candle_index": 475,
    "zone_top": 81145.9,
    "zone_bottom": 81054.2,
    "vwap_at_detection": 81100.25184760257,
    "detection_timestamp": 1778501999999,
    "direction": "bearish",
    "key_candle": {
      "index": 475,
      "open": 81054.0,
      "high": 81154.6,
      "low": 81027.8,
      "close": 81092.4,
      "volume": 566.728,
      "vol_z_score": 2.5427028160739487,
      "body_percentage": 30.283911671919004,
      "upper_wick_pct": 49.05362776026042,
      "lower_wick_pct": 20.662460567820574,
      "rejection_direction": "UP",
      "timestamp": 1778501700000
    },
    "accumulation_zone": {
      "start_idx": 464,
      "end_idx": 471,
      "high": 81145.9,
      "low": 81054.2,
      "volume_avg": 244.67357142857145,
      "vwap": 81100.25184760257,
      "mfi": 50,
      "quality_score": 1.0340847370068862
    },
    "mini_trend": {
      "start_idx": 476,
      "end_idx": 481,
      "direction": "bearish",
      "start_price": 81271.2,
      "end_price": 81110.9,
      "slope": -35.051428571432545,
      "slope_normalized": 0.043169601675272576,
      "r2": 0.9548753491075234
    },
    "atr_at_detection": 358.1999999999971,
    "lifecycle_state": "active",
    "touch_count": 0,
    "polarity_flipped": false,
    "zone_id": ""
  },
  {
    "candle_index": 57,
    "zone_top": 80918.0,
    "zone_bottom": 80825.0,
    "vwap_at_detection": 80879.46136323341,
    "detection_timestamp": 1778419799999,
    "direction": "bearish",
    "key_candle": {
      "index": 57,
      "open": 80926.1,
      "high": 80970.0,
      "low": 80910.4,
      "close": 80937.6,
      "volume": 267.507,
      "vol_z_score": 1.215135194791017,
      "body_percentage": 19.295302013420933,
      "upper_wick_pct": 54.36241610736747,
      "lower_wick_pct": 26.34228187921159,
      "rejection_direction": "UP",
      "timestamp": 1778419500000
    },
    "accumulation_zone": {
      "start_idx": 45,
      "end_idx": 56,
      "high": 80918.0,
      "low": 80825.0,
      "volume_avg": 117.59163636363638,
      "vwap": 80879.46136323341,
      "mfi": 50,
      "quality_score": 0.9980521941974086
    },
    "mini_trend": {
      "start_idx": 58,
      "end_idx": 73,
      "direction": "bearish",
      "start_price": 80959.9,
      "end_price": 80786.2,
      "slope": -6.177647058821088,
      "slope_normalized": 0.007636214646159603,
      "r2": 0.5522720013617414
    },
    "atr_at_detection": 164.8000000000029,
    "lifecycle_state": "active",
    "touch_count": 0,
    "polarity_flipped": false,
    "zone_id": ""
  },
  {
    "candle_index": 66,
    "zone_top": 80970.0,
    "zone_bottom": 80888.5,
    "vwap_at_detection": 80930.2333353835,
    "detection_timestamp": 1778422499999,
    "direction": "bearish",
    "key_candle": {
      "index": 66,
      "open": 80892.4,
      "high": 80940.5,
      "low": 80890.6,
      "close": 80892.4,
      "volume": 164.72,
      "vol_z_score": 1.0383386339160419,
      "body_percentage": 0.0,
      "upper_wick_pct": 96.39278557116519,
      "lower_wick_pct": 3.6072144288348067,
      "rejection_direction": "UP",
      "timestamp": 1778422200000
    },
    "accumulation_zone": {
      "start_idx": 57,
      "end_idx": 65,
      "high": 80970.0,
      "low": 80888.5,
      "volume_avg": 128.03924999999998,
      "vwap": 80930.2333353835,
      "mfi": 50,
      "quality_score": 1.0342254663422548
    },
    "mini_trend": {
      "start_idx": 58,
      "end_idx": 73,
      "direction": "bearish",
      "start_price": 80959.9,
      "end_price": 80786.2,
      "slope": -6.177647058821088,
      "slope_normalized": 0.007636214646159603,
      "r2": 0.5522720013617414
    },
    "atr_at_detection": 145.0,
    "lifecycle_state": "active",
    "touch_count": 0,
    "polarity_flipped": false,
    "zone_id": ""
  },
  {
    "candle_index": 327,
    "zone_top": 81145.9,
    "zone_bottom": 81054.2,
    "vwap_at_detection": 81100.25184760257,
    "detection_timestamp": 1778500799999,
    "direction": "bearish",
    "key_candle": {
      "index": 327,
      "open": 81138.7,
      "high": 81172.6,
      "low": 81100.0,
      "close": 81167.1,
      "volume": 315.673,
      "vol_z_score": 0.8087489864203525,
      "body_percentage": 39.11845730028437,
      "upper_wick_pct": 7.575757575756969,
      "lower_wick_pct": 53.30578512395866,
      "rejection_direction": "DOWN",
      "timestamp": 1778500500000
    },
    "accumulation_zone": {
      "start_idx": 320,
      "end_idx": 327,
      "high": 81145.9,
      "low": 81054.2,
      "volume_avg": 244.67357142857145,
      "vwap": 81100.25184760257,
      "mfi": 50,
      "quality_score": 1.0607514036735528
    },
    "mini_trend": {
      "start_idx": 332,
      "end_idx": 337,
      "direction": "bearish",
      "start_price": 81271.2,
      "end_price": 81110.9,
      "slope": -35.051428571432545,
      "slope_normalized": 0.043169601675272576,
      "r2": 0.9548753491075234
    },
    "atr_at_detection": 312.6000000000058,
    "lifecycle_state": "active",
    "touch_count": 0,
    "polarity_flipped": false,
    "zone_id": ""
  },
  {
    "candle_index": 328,
    "zone_top": 81145.9,
    "zone_bottom": 81054.2,
    "vwap_at_detection": 81100.25184760257,
    "detection_timestamp": 1778501099999,
    "direction": "bearish",
    "key_candle": {
      "index": 328,
      "open": 81167.1,
      "high": 81218.2,
      "low": 81108.0,
      "close": 81130.4,
      "volume": 584.857,
      "vol_z_score": 3.2016682823888205,
      "body_percentage": 33.30308529946698,
      "upper_wick_pct": 46.37023593465755,
      "lower_wick_pct": 20.32667876587547,
      "rejection_direction": "UP",
      "timestamp": 1778500800000
    },
    "accumulation_zone": {
      "start_idx": 320,
      "end_idx": 327,
      "high": 81145.9,
      "low": 81054.2,
      "volume_avg": 244.67357142857145,
      "vwap": 81100.25184760257,
      "mfi": 50,
      "quality_score": 1.0540847370068862
    },
    "mini_trend": {
      "start_idx": 332,
      "end_idx": 337,
      "direction": "bearish",
      "start_price": 81271.2,
      "end_price": 81110.9,
      "slope": -35.051428571432545,
      "slope_normalized": 0.043169601675272576,
      "r2": 0.9548753491075234
    },
    "atr_at_detection": 358.1999999999971,
    "lifecycle_state": "active",
    "touch_count": 0,
    "polarity_flipped": false,
    "zone_id": ""
  },
  {
    "candle_index": 331,
    "zone_top": 81145.9,
    "zone_bottom": 81054.2,
    "vwap_at_detection": 81100.25184760257,
    "detection_timestamp": 1778501999999,
    "direction": "bearish",
    "key_candle": {
      "index": 331,
      "open": 81054.0,
      "high": 81154.6,
      "low": 81027.8,
      "close": 81092.4,
      "volume": 566.728,
      "vol_z_score": 2.5427028160739487,
      "body_percentage": 30.283911671919004,
      "upper_wick_pct": 49.05362776026042,
      "lower_wick_pct": 20.662460567820574,
      "rejection_direction": "UP",
      "timestamp": 1778501700000
    },
    "accumulation_zone": {
      "start_idx": 320,
      "end_idx": 327,
      "high": 81145.9,
      "low": 81054.2,
      "volume_avg": 244.67357142857145,
      "vwap": 81100.25184760257,
      "mfi": 50,
      "quality_score": 1.0340847370068862
    },
    "mini_trend": {
      "start_idx": 332,
      "end_idx": 337,
      "direction": "bearish",
      "start_price": 81271.2,
      "end_price": 81110.9,
      "slope": -35.051428571432545,
      "slope_normalized": 0.043169601675272576,
      "r2": 0.9548753491075234
    },
    "atr_at_detection": 358.1999999999971,
    "lifecycle_state": "active",
    "touch_count": 0,
    "polarity_flipped": false,
    "zone_id": ""
  },
  {
    "candle_index": 358,
    "zone_top": 81221.0,
    "zone_bottom": 80900.0,
    "vwap_at_detection": 81111.21520693158,
    "detection_timestamp": 1778510099999,
    "direction": "bullish",
    "key_candle": {
      "index": 358,
      "open": 80709.7,
      "high": 80791.3,
      "low": 80394.0,
      "close": 80569.1,
      "volume": 3260.806,
      "vol_z_score": 8.236320845032473,
      "body_percentage": 35.38887490561043,
      "upper_wick_pct": 20.53863579159457,
      "lower_wick_pct": 44.072489302795,
      "rejection_direction": "DOWN",
      "timestamp": 1778509800000
    },
    "accumulation_zone": {
      "start_idx": 351,
      "end_idx": 356,
      "high": 81221.0,
      "low": 80900.0,
      "volume_avg": 437.68899999999996,
      "vwap": 81111.21520693158,
      "mfi": 50,
      "quality_score": 0.9734226523875645
    },
    "mini_trend": {
      "start_idx": 362,
      "end_idx": 368,
      "direction": "bullish",
      "start_price": 80859.9,
      "end_price": 81019.8,
      "slope": 20.671428571431008,
      "slope_normalized": 0.025545110953524148,
      "r2": 0.5846596064579886
    },
    "atr_at_detection": 859.1999999999971,
    "lifecycle_state": "active",
    "touch_count": 0,
    "polarity_flipped": false,
    "zone_id": ""
  },
  {
    "candle_index": 379,
    "zone_top": 81399.0,
    "zone_bottom": 81160.8,
    "vwap_at_detection": 81237.41072771828,
    "detection_timestamp": 1778516399999,
    "direction": "bullish",
    "key_candle": {
      "index": 379,
      "open": 81751.6,
      "high": 81792.5,
      "low": 81629.3,
      "close": 81787.2,
      "volume": 1126.165,
      "vol_z_score": 0.5753007750488944,
      "body_percentage": 21.813725490191118,
      "upper_wick_pct": 3.2475490196096843,
      "lower_wick_pct": 74.9387254901992,
      "rejection_direction": "DOWN",
      "timestamp": 1778516100000
    },
    "accumulation_zone": {
      "start_idx": 370,
      "end_idx": 375,
      "high": 81399.0,
      "low": 81160.8,
      "volume_avg": 465.1103999999999,
      "vwap": 81237.41072771828,
      "mfi": 50,
      "quality_score": 1.0327384320455177
    },
    "mini_trend": {
      "start_idx": 369,
      "end_idx": 377,
      "direction": "bullish",
      "start_price": 81302.0,
      "end_price": 81533.0,
      "slope": 29.840000000000714,
      "slope_normalized": 0.03670532780785389,
      "r2": 0.4945223669968041
    },
    "atr_at_detection": 969.6999999999971,
    "lifecycle_state": "active",
    "touch_count": 0,
    "polarity_flipped": false,
    "zone_id": ""
  },
  {
    "candle_index": 397,
    "zone_top": 81635.9,
    "zone_bottom": 81322.3,
    "vwap_at_detection": 81487.42769553846,
    "detection_timestamp": 1778521799999,
    "direction": "bullish",
    "key_candle": {
      "index": 397,
      "open": 81936.4,
      "high": 82033.8,
      "low": 81874.1,
      "close": 81909.9,
      "volume": 1084.385,
      "vol_z_score": 0.7464335971177528,
      "body_percentage": 16.593613024421092,
      "upper_wick_pct": 60.98935504070789,
      "lower_wick_pct": 22.417031934871016,
      "rejection_direction": "UP",
      "timestamp": 1778521500000
    },
    "accumulation_zone": {
      "start_idx": 387,
      "end_idx": 392,
      "high": 81635.9,
      "low": 81322.3,
      "volume_avg": 502.0308,
      "vwap": 81487.42769553846,
      "mfi": 50,
      "quality_score": 0.969356531665537
    },
    "mini_trend": {
      "start_idx": 395,
      "end_idx": 401,
      "direction": "bullish",
      "start_price": 81821.6,
      "end_price": 82005.0,
      "slope": 20.19642857142768,
      "slope_normalized": 0.02465539991189346,
      "r2": 0.5703885374021955
    },
    "atr_at_detection": 711.5,
    "lifecycle_state": "active",
    "touch_count": 0,
    "polarity_flipped": false,
    "zone_id": ""
  },
  {
    "candle_index": 485,
    "zone_top": 81641.5,
    "zone_bottom": 81480.0,
    "vwap_at_detection": 81544.63919485731,
    "detection_timestamp": 1778548199999,
    "direction": "bearish",
    "key_candle": {
      "index": 485,
      "open": 81428.9,
      "high": 81489.7,
      "low": 81358.1,
      "close": 81396.7,
      "volume": 412.973,
      "vol_z_score": 1.832587821387303,
      "body_percentage": 24.46808510638239,
      "upper_wick_pct": 46.20060790274084,
      "lower_wick_pct": 29.33130699087677,
      "rejection_direction": "UP",
      "timestamp": 1778547900000
    },
    "accumulation_zone": {
      "start_idx": 475,
      "end_idx": 480,
      "high": 81641.5,
      "low": 81480.0,
      "volume_avg": 337.9724,
      "vwap": 81544.63919485731,
      "mfi": 50,
      "quality_score": 0.9340790043238785
    },
    "mini_trend": {
      "start_idx": 480,
      "end_idx": 490,
      "direction": "bearish",
      "start_price": 81451.3,
      "end_price": 81107.9,
      "slope": -30.50727272727175,
      "slope_normalized": 0.03748139082117946,
      "r2": 0.726580582383318
    },
    "atr_at_detection": 399.1999999999971,
    "lifecycle_state": "active",
    "touch_count": 0,
    "polarity_flipped": false,
    "zone_id": ""
  },
  {
    "candle_index": 57,
    "zone_top": 80918.0,
    "zone_bottom": 80825.0,
    "vwap_at_detection": 80879.46136323341,
    "detection_timestamp": 1778419799999,
    "direction": "bearish",
    "key_candle": {
      "index": 57,
      "open": 80926.1,
      "high": 80970.0,
      "low": 80910.4,
      "close": 80937.6,
      "volume": 267.507,
      "vol_z_score": 1.215135194791017,
      "body_percentage": 19.295302013420933,
      "upper_wick_pct": 54.36241610736747,
      "lower_wick_pct": 26.34228187921159,
      "rejection_direction": "UP",
      "timestamp": 1778419500000
    },
    "accumulation_zone": {
      "start_idx": 45,
      "end_idx": 56,
      "high": 80918.0,
      "low": 80825.0,
      "volume_avg": 117.59163636363638,
      "vwap": 80879.46136323341,
      "mfi": 50,
      "quality_score": 0.9980521941974086
    },
    "mini_trend": {
      "start_idx": 58,
      "end_idx": 73,
      "direction": "bearish",
      "start_price": 80959.9,
      "end_price": 80786.2,
      "slope": -6.177647058821088,
      "slope_normalized": 0.007636214646159603,
      "r2": 0.5522720013617414
    },
    "atr_at_detection": 164.8000000000029,
    "lifecycle_state": "active",
    "touch_count": 0,
    "polarity_flipped": false,
    "zone_id": ""
  },
  {
    "candle_index": 66,
    "zone_top": 80970.0,
    "zone_bottom": 80888.5,
    "vwap_at_detection": 80930.2333353835,
    "detection_timestamp": 1778422499999,
    "direction": "bearish",
    "key_candle": {
      "index": 66,
      "open": 80892.4,
      "high": 80940.5,
      "low": 80890.6,
      "close": 80892.4,
      "volume": 164.72,
      "vol_z_score": 1.0383386339160419,
      "body_percentage": 0.0,
      "upper_wick_pct": 96.39278557116519,
      "lower_wick_pct": 3.6072144288348067,
      "rejection_direction": "UP",
      "timestamp": 1778422200000
    },
    "accumulation_zone": {
      "start_idx": 57,
      "end_idx": 65,
      "high": 80970.0,
      "low": 80888.5,
      "volume_avg": 128.03924999999998,
      "vwap": 80930.2333353835,
      "mfi": 50,
      "quality_score": 1.0342254663422548
    },
    "mini_trend": {
      "start_idx": 58,
      "end_idx": 73,
      "direction": "bearish",
      "start_price": 80959.9,
      "end_price": 80786.2,
      "slope": -6.177647058821088,
      "slope_normalized": 0.007636214646159603,
      "r2": 0.5522720013617414
    },
    "atr_at_detection": 145.0,
    "lifecycle_state": "active",
    "touch_count": 0,
    "polarity_flipped": false,
    "zone_id": ""
  },
  {
    "candle_index": 327,
    "zone_top": 81145.9,
    "zone_bottom": 81054.2,
    "vwap_at_detection": 81100.25184760257,
    "detection_timestamp": 1778500799999,
    "direction": "bearish",
    "key_candle": {
      "index": 327,
      "open": 81138.7,
      "high": 81172.6,
      "low": 81100.0,
      "close": 81167.1,
      "volume": 315.673,
      "vol_z_score": 0.8087489864203525,
      "body_percentage": 39.11845730028437,
      "upper_wick_pct": 7.575757575756969,
      "lower_wick_pct": 53.30578512395866,
      "rejection_direction": "DOWN",
      "timestamp": 1778500500000
    },
    "accumulation_zone": {
      "start_idx": 320,
      "end_idx": 327,
      "high": 81145.9,
      "low": 81054.2,
      "volume_avg": 244.67357142857145,
      "vwap": 81100.25184760257,
      "mfi": 50,
      "quality_score": 1.0607514036735528
    },
    "mini_trend": {
      "start_idx": 332,
      "end_idx": 337,
      "direction": "bearish",
      "start_price": 81271.2,
      "end_price": 81110.9,
      "slope": -35.051428571432545,
      "slope_normalized": 0.043169601675272576,
      "r2": 0.9548753491075234
    },
    "atr_at_detection": 312.6000000000058,
    "lifecycle_state": "active",
    "touch_count": 0,
    "polarity_flipped": false,
    "zone_id": ""
  },
  {
    "candle_index": 328,
    "zone_top": 81145.9,
    "zone_bottom": 81054.2,
    "vwap_at_detection": 81100.25184760257,
    "detection_timestamp": 1778501099999,
    "direction": "bearish",
    "key_candle": {
      "index": 328,
      "open": 81167.1,
      "high": 81218.2,
      "low": 81108.0,
      "close": 81130.4,
      "volume": 584.857,
      "vol_z_score": 3.2016682823888205,
      "body_percentage": 33.30308529946698,
      "upper_wick_pct": 46.37023593465755,
      "lower_wick_pct": 20.32667876587547,
      "rejection_direction": "UP",
      "timestamp": 1778500800000
    },
    "accumulation_zone": {
      "start_idx": 320,
      "end_idx": 327,
      "high": 81145.9,
      "low": 81054.2,
      "volume_avg": 244.67357142857145,
      "vwap": 81100.25184760257,
      "mfi": 50,
      "quality_score": 1.0540847370068862
    },
    "mini_trend": {
      "start_idx": 332,
      "end_idx": 337,
      "direction": "bearish",
      "start_price": 81271.2,
      "end_price": 81110.9,
      "slope": -35.051428571432545,
      "slope_normalized": 0.043169601675272576,
      "r2": 0.9548753491075234
    },
    "atr_at_detection": 358.1999999999971,
    "lifecycle_state": "active",
    "touch_count": 0,
    "polarity_flipped": false,
    "zone_id": ""
  },
  {
    "candle_index": 331,
    "zone_top": 81145.9,
    "zone_bottom": 81054.2,
    "vwap_at_detection": 81100.25184760257,
    "detection_timestamp": 1778501999999,
    "direction": "bearish",
    "key_candle": {
      "index": 331,
      "open": 81054.0,
      "high": 81154.6,
      "low": 81027.8,
      "close": 81092.4,
      "volume": 566.728,
      "vol_z_score": 2.5427028160739487,
      "body_percentage": 30.283911671919004,
      "upper_wick_pct": 49.05362776026042,
      "lower_wick_pct": 20.662460567820574,
      "rejection_direction": "UP",
      "timestamp": 1778501700000
    },
    "accumulation_zone": {
      "start_idx": 320,
      "end_idx": 327,
      "high": 81145.9,
      "low": 81054.2,
      "volume_avg": 244.67357142857145,
      "vwap": 81100.25184760257,
      "mfi": 50,
      "quality_score": 1.0340847370068862
    },
    "mini_trend": {
      "start_idx": 332,
      "end_idx": 337,
      "direction": "bearish",
      "start_price": 81271.2,
      "end_price": 81110.9,
      "slope": -35.051428571432545,
      "slope_normalized": 0.043169601675272576,
      "r2": 0.9548753491075234
    },
    "atr_at_detection": 358.1999999999971,
    "lifecycle_state": "active",
    "touch_count": 0,
    "polarity_flipped": false,
    "zone_id": ""
  },
  {
    "candle_index": 358,
    "zone_top": 81221.0,
    "zone_bottom": 80900.0,
    "vwap_at_detection": 81111.21520693158,
    "detection_timestamp": 1778510099999,
    "direction": "bullish",
    "key_candle": {
      "index": 358,
      "open": 80709.7,
      "high": 80791.3,
      "low": 80394.0,
      "close": 80569.1,
      "volume": 3260.806,
      "vol_z_score": 8.236320845032473,
      "body_percentage": 35.38887490561043,
      "upper_wick_pct": 20.53863579159457,
      "lower_wick_pct": 44.072489302795,
      "rejection_direction": "DOWN",
      "timestamp": 1778509800000
    },
    "accumulation_zone": {
      "start_idx": 351,
      "end_idx": 356,
      "high": 81221.0,
      "low": 80900.0,
      "volume_avg": 437.68899999999996,
      "vwap": 81111.21520693158,
      "mfi": 50,
      "quality_score": 0.9734226523875645
    },
    "mini_trend": {
      "start_idx": 362,
      "end_idx": 368,
      "direction": "bullish",
      "start_price": 80859.9,
      "end_price": 81019.8,
      "slope": 20.671428571431008,
      "slope_normalized": 0.025545110953524148,
      "r2": 0.5846596064579886
    },
    "atr_at_detection": 859.1999999999971,
    "lifecycle_state": "active",
    "touch_count": 0,
    "polarity_flipped": false,
    "zone_id": ""
  },
  {
    "candle_index": 379,
    "zone_top": 81399.0,
    "zone_bottom": 81160.8,
    "vwap_at_detection": 81237.41072771828,
    "detection_timestamp": 1778516399999,
    "direction": "bullish",
    "key_candle": {
      "index": 379,
      "open": 81751.6,
      "high": 81792.5,
      "low": 81629.3,
      "close": 81787.2,
      "volume": 1126.165,
      "vol_z_score": 0.5753007750488944,
      "body_percentage": 21.813725490191118,
      "upper_wick_pct": 3.2475490196096843,
      "lower_wick_pct": 74.9387254901992,
      "rejection_direction": "DOWN",
      "timestamp": 1778516100000
    },
    "accumulation_zone": {
      "start_idx": 370,
      "end_idx": 375,
      "high": 81399.0,
      "low": 81160.8,
      "volume_avg": 465.1103999999999,
      "vwap": 81237.41072771828,
      "mfi": 50,
      "quality_score": 1.0327384320455177
    },
    "mini_trend": {
      "start_idx": 369,
      "end_idx": 377,
      "direction": "bullish",
      "start_price": 81302.0,
      "end_price": 81533.0,
      "slope": 29.840000000000714,
      "slope_normalized": 0.03670532780785389,
      "r2": 0.4945223669968041
    },
    "atr_at_detection": 969.6999999999971,
    "lifecycle_state": "active",
    "touch_count": 0,
    "polarity_flipped": false,
    "zone_id": ""
  },
  {
    "candle_index": 397,
    "zone_top": 81635.9,
    "zone_bottom": 81322.3,
    "vwap_at_detection": 81487.42769553846,
    "detection_timestamp": 1778521799999,
    "direction": "bullish",
    "key_candle": {
      "index": 397,
      "open": 81936.4,
      "high": 82033.8,
      "low": 81874.1,
      "close": 81909.9,
      "volume": 1084.385,
      "vol_z_score": 0.7464335971177528,
      "body_percentage": 16.593613024421092,
      "upper_wick_pct": 60.98935504070789,
      "lower_wick_pct": 22.417031934871016,
      "rejection_direction": "UP",
      "timestamp": 1778521500000
    },
    "accumulation_zone": {
      "start_idx": 387,
      "end_idx": 392,
      "high": 81635.9,
      "low": 81322.3,
      "volume_avg": 502.0308,
      "vwap": 81487.42769553846,
      "mfi": 50,
      "quality_score": 0.969356531665537
    },
    "mini_trend": {
      "start_idx": 395,
      "end_idx": 401,
      "direction": "bullish",
      "start_price": 81821.6,
      "end_price": 82005.0,
      "slope": 20.19642857142768,
      "slope_normalized": 0.02465539991189346,
      "r2": 0.5703885374021955
    },
    "atr_at_detection": 711.5,
    "lifecycle_state": "active",
    "touch_count": 0,
    "polarity_flipped": false,
    "zone_id": ""
  },
  {
    "candle_index": 485,
    "zone_top": 81641.5,
    "zone_bottom": 81480.0,
    "vwap_at_detection": 81544.63919485731,
    "detection_timestamp": 1778548199999,
    "direction": "bearish",
    "key_candle": {
      "index": 485,
      "open": 81428.9,
      "high": 81489.7,
      "low": 81358.1,
      "close": 81396.7,
      "volume": 412.973,
      "vol_z_score": 1.832587821387303,
      "body_percentage": 24.46808510638239,
      "upper_wick_pct": 46.20060790274084,
      "lower_wick_pct": 29.33130699087677,
      "rejection_direction": "UP",
      "timestamp": 1778547900000
    },
    "accumulation_zone": {
      "start_idx": 475,
      "end_idx": 480,
      "high": 81641.5,
      "low": 81480.0,
      "volume_avg": 337.9724,
      "vwap": 81544.63919485731,
      "mfi": 50,
      "quality_score": 0.9340790043238785
    },
    "mini_trend": {
      "start_idx": 480,
      "end_idx": 490,
      "direction": "bearish",
      "start_price": 81451.3,
      "end_price": 81107.9,
      "slope": -30.50727272727175,
      "slope_normalized": 0.03748139082117946,
      "r2": 0.726580582383318
    },
    "atr_at_detection": 399.1999999999971,
    "lifecycle_state": "active",
    "touch_count": 0,
    "polarity_flipped": false,
    "zone_id": ""
  }
]